openbb_government_us/__init__.py
openbb_government_us/models/__init__.py
openbb_government_us/models/treasury_auctions.py
openbb_government_us/models/treasury_prices.py
openbb_government_us/utils/__init__.py
openbb_government_us/utils/helpers.py
openbb_government_us-1.5.1.dist-info/METADATA
openbb_government_us-1.5.1.dist-info/WHEEL
openbb_government_us-1.5.1.dist-info/entry_points.txt
openbb_government_us-1.5.1.dist-info/RECORD
